cpfValidationTool/__init__.py
cpfValidationTool/cpfValidation/__init__.py
cpfValidationTool/cpfValidation/cpf.py
cpfValidationTool-0.0.2.dist-info/METADATA
cpfValidationTool-0.0.2.dist-info/WHEEL
cpfValidationTool-0.0.2.dist-info/top_level.txt
cpfValidationTool-0.0.2.dist-info/RECORD
