Metadata-Version: 2.1
Name: cpfValidationTool
Version: 0.0.2
Summary: Código que valida o CPF através da validação dos últimos dois dígitos
Home-page: https://github.com/rodrigofmfreitas/dio-cursos/tree/main/Geracao-Tech-Unimed/Desafio2
Author: Rodrigo Freitas
Author-email: digofmf@gmail.com
Requires-Python: >=3.5
